neuralNetworkGA.py
NNGA-0.0.7.dist-info/METADATA
NNGA-0.0.7.dist-info/WHEEL
NNGA-0.0.7.dist-info/top_level.txt
NNGA-0.0.7.dist-info/RECORD
