Metadata-Version: 2.1
Name: NNGA
Version: 0.0.7
Summary: A neural networks combine genetic algorithm module.
Home-page: UNKNOWN
Author: maigua
Author-email: 3075489925@qq.com
License: UNKNOWN
Platform: UNKNOWN
Requires-Dist: numpy
